geox/__init__.py
geox/config.py
geox/connection.py
geox/exceptions.py
geox/geox.py
geox/geox_file.py
geox/project.py
geox/project_version.py
geox/utils.py
geox/version.py
geox/api_caller/__init__.py
geox/api_caller/get_dataset.py
geox/api_caller/get_initial_auth.py
geox/api_caller/get_project.py
geox/api_caller/get_project_version.py
geox/api_caller/get_project_versions.py
geox/api_caller/get_projects.py
geox/entity/__init__.py
geox/entity/api_endpoint.py
geox/entity/dataset_columns.py
geox/entity/dataset_type.py
geox/factory/__init__.py
geox/factory/factory.py
geox/factory/project_factory.py
geox/factory/project_version_factory.py
geox/http_response/__init__.py
geox/http_response/http_dataset.py
geox/http_response/http_initial_auth.py
geox/http_response/http_project.py
geox/http_response/http_project_version.py
geox/http_response/http_project_versions.py
geox/http_response/http_projects.py
geox-0.0.14.dist-info/LICENSE
geox-0.0.14.dist-info/METADATA
geox-0.0.14.dist-info/WHEEL
geox-0.0.14.dist-info/top_level.txt
geox-0.0.14.dist-info/RECORD
